kion_pgvectorstore/.env
kion_pgvectorstore/README.md
kion_pgvectorstore/__init__.py
kion_pgvectorstore/app.py
kion_pgvectorstore/base.py
kion_pgvectorstore/cli_init_env.py
kion_pgvectorstore/config.py
kion_pgvectorstore/document.py
kion_pgvectorstore/dotenv_finder.py
kion_pgvectorstore/embeddings.py
kion_pgvectorstore/file_loader.py
kion_pgvectorstore/llm.py
kion_pgvectorstore/manage_vectorstore.py
kion_pgvectorstore/pdf_file_loader.py
kion_pgvectorstore/pdf_image_loader.py
kion_pgvectorstore/pgvector_plugin.py
kion_pgvectorstore/recursive_text_splitter.py
kion_pgvectorstore/setup_config.py
kion_pgvectorstore/text_file_loader.py
kion_pgvectorstore/static/chat.html
kion_pgvectorstore/static/file_loader_gui.html
kion_pgvectorstore/static/file_remover_gui.html
kion_pgvectorstore-0.1.0.dist-info/licenses/LICENSE
kion_pgvectorstore-0.1.0.dist-info/METADATA
kion_pgvectorstore-0.1.0.dist-info/WHEEL
kion_pgvectorstore-0.1.0.dist-info/top_level.txt
kion_pgvectorstore-0.1.0.dist-info/RECORD
