Metadata-Version: 2.4
Name: kion-pgvectorstore
Version: 0.1.0
Summary: A Python library for managing vector stores.
Home-page: https://github.com/yourusername/kion_pgvectorstore
Author: Kion Consulting
Author-email: Kion Consulting <thoriso@kion.co.za>
License: MIT License
Requires-Python: >=3.8
License-File: LICENSE
Requires-Dist: flask
Requires-Dist: flask-cors
Requires-Dist: python-dotenv
Requires-Dist: openai
Requires-Dist: tiktoken
Requires-Dist: sqlalchemy
Requires-Dist: psycopg2-binary
Requires-Dist: pgvector
Requires-Dist: numpy
Requires-Dist: sentence-transformers
Requires-Dist: Pillow
Requires-Dist: PyMuPDF
Requires-Dist: pypdf
Requires-Dist: PyPDF2
Requires-Dist: importlib-resources
Dynamic: author
Dynamic: home-page
Dynamic: license-file
Dynamic: requires-python
